sum_comparison/Labb3.py
sum_comparison/__init__.py
sum_comparison/typed_input.py
sum_comparison-1.0.dist-info/METADATA
sum_comparison-1.0.dist-info/WHEEL
sum_comparison-1.0.dist-info/licenses/LICENSE
sum_comparison-1.0.dist-info/RECORD
