Metadata-Version: 2.1
Name: sum_comparison
Version: 1.0
Summary: A package that compares two sums
Project-URL: homepage, https://github.com/egrochka/KTH_labbar
Author: Jegors, Linus
License-File: LICENSE
Classifier: Operating System :: OS Independent
Classifier: Programming Language :: Python :: 3
Requires-Python: >=3.7
